{
 "Saudi Arabia": {
  "code": "sa",
  "currency": "SAR",
  "currency_fraction": "Halala",
  "currency_fraction_units": 100,
  "currency_name": "Saudi Riyal",
  "currency_symbol": "\u0631.\u0633",
  "number_format": "#,###.##",
  "timezones": [
   "Asia/Riyadh"
  ]
 },
 "India": {
  "code": "in",
  "currency": "INR",
  "currency_fraction": "Paisa",
  "currency_fraction_units": 100,
  "currency_name": "Indian Rupee",
  "currency_symbol": "\u20b9",
  "number_format": "#,##,###.##",
  "timezones": [
   "Asia/Kolkata"
  ]
 }
}